new_fave/__init__.py
new_fave/extract.py
new_fave/measurements/__init__.py
new_fave/measurements/calcs.py
new_fave/measurements/decorators.py
new_fave/measurements/reference.py
new_fave/measurements/vowel_measurement.py
new_fave/optimize/__init__.py
new_fave/optimize/left_edge.py
new_fave/optimize/optimize.py
new_fave/patterns/__init__.py
new_fave/patterns/common_processing.py
new_fave/patterns/fave_audio_textgrid.py
new_fave/patterns/fave_corpus.py
new_fave/patterns/fave_subcorpora.py
new_fave/patterns/writers.py
new_fave/resources/cmu2labov.yml
new_fave/resources/cmu2phila.yml
new_fave/resources/cmu_parser.yml
new_fave/resources/fasttrack_config.yml
new_fave/resources/fave_measurement.yml
new_fave/resources/norecode.yml
new_fave/resources/vowel_place.yml
new_fave/speaker/__init__.py
new_fave/speaker/speaker.py
new_fave/utils/__init__.py
new_fave/utils/corpus.py
new_fave/utils/fasttrack_config.py
new_fave/utils/local_resources.py
new_fave/utils/safely.py
new_fave/utils/textgrid.py
new_fave/utils/vowel_place.py
new_fave-1.2.1.dist-info/LICENSE
new_fave-1.2.1.dist-info/METADATA
new_fave-1.2.1.dist-info/WHEEL
new_fave-1.2.1.dist-info/entry_points.txt
new_fave-1.2.1.dist-info/RECORD
