Metadata-Version: 2.3
Name: new-fave
Version: 1.2.1
Summary: New Vowel Extraction Suite
License: GPLv3
Author: JoFrhwld
Author-email: jofrhwld@gmail.com
Requires-Python: >=3.10,<3.14
Classifier: License :: Other/Proprietary License
Classifier: Programming Language :: Python :: 3
Classifier: Programming Language :: Python :: 3.10
Classifier: Programming Language :: Python :: 3.11
Classifier: Programming Language :: Python :: 3.12
Classifier: Programming Language :: Python :: 3.13
Requires-Dist: aligned-textgrid (>=0.8,<0.9)
Requires-Dist: click (>=8.1.7,<9.0.0)
Requires-Dist: cloudpickle (>=3.0.0,<4.0.0)
Requires-Dist: cloup (>=3.0.5,<4.0.0)
Requires-Dist: fastexcel (>=0.13.0,<0.14.0)
Requires-Dist: fasttrackpy (>=0.5.3,<0.6.0)
Requires-Dist: fave-measurement-point (>=0.1.5,<0.2.0)
Requires-Dist: fave-recode (>=0.3.0,<0.4.0)
Requires-Dist: librosa (>=0.10.2.post1,<0.11.0)
Requires-Dist: numpy (<=2.2)
Requires-Dist: polars (>=1.23.0,<2.0.0)
Requires-Dist: python-magic (>=0.4.27,<0.5.0) ; sys_platform != "win32"
Requires-Dist: python-magic-bin (>=0.4.14,<0.5.0) ; sys_platform == "win32"
Requires-Dist: scipy (>=1.13.1,<2.0.0)
Requires-Dist: toml (>=0.10.2,<0.11.0)
Requires-Dist: tqdm (>=4.66.2,<5.0.0)
Requires-Dist: xlsx2csv (>=0.8.2,<0.9.0)
Project-URL: Homepage, https://forced-alignment-and-vowel-extraction.github.io/new-fave/
Project-URL: Repository, https://github.com/Forced-Alignment-and-Vowel-Extraction/new-fave
